{
    "$schema": "http://schema.management.azure.com/schemas/2015-01-01/deploymentParameters.json#",
    "contentVersion": "1.0.0.0",
    "parameters": {
        "pipelineResourceNamesPrefix":{
            "value": "inloc"
        },
        "storageAccountType": {
            "value": "Standard_LRS"
        },
        "eventHubsNamespaceSkuName":{
            "value": "Standard"
        },
        "eventHubsNamespaceSkuTier": {
            "value": "Standard"
        },
        "eventHubsNamespaceIsAutoInflateEnabled": {
            "value": false
        },
        "cosmosDbSku": {
            "value": "Standard"
        },
        "appServiceSku": {
            "value": "Standard"
        },
        "appServiceSkuCode": {
            "value": "S1"
        },
        "appServiceWorkerSize": {
            "value": "0"
        },
        "cmxListenerDockerImageName": {
            "value": "jcorioland/cmx-listener:latest"
        },
        "redisCacheSku": {
            "value": "Standard"
        },
        "redisCacheFamily": {
            "value": "C"
        },
        "redisCacheCapacity": {
            "value": 1
        }
    }
  }